reolinkfw/__init__.py
reolinkfw/__main__.py
reolinkfw/fdt.py
reolinkfw/tmpfile.py
reolinkfw/typedefs.py
reolinkfw/ubifs.py
reolinkfw/uboot.py
reolinkfw/util.py
reolinkfw-2.0.0.dist-info/LICENSE
reolinkfw-2.0.0.dist-info/METADATA
reolinkfw-2.0.0.dist-info/WHEEL
reolinkfw-2.0.0.dist-info/entry_points.txt
reolinkfw-2.0.0.dist-info/top_level.txt
reolinkfw-2.0.0.dist-info/RECORD
