Metadata-Version: 2.1
Name: reolinkfw
Version: 2.0.0
Summary: Extract information and files from Reolink firmwares.
Author-email: AT0myks <at0myks.dev@gmail.com>
Project-URL: Issues, https://github.com/AT0myks/reolink-fw/issues
Project-URL: Source, https://github.com/AT0myks/reolink-fw
Keywords: reolink,firmware
Classifier: Development Status :: 5 - Production/Stable
Classifier: Intended Audience :: Developers
Classifier: Intended Audience :: End Users/Desktop
Classifier: License :: OSI Approved :: GNU General Public License v3 (GPLv3)
Classifier: Operating System :: OS Independent
Classifier: Programming Language :: Python :: 3
Classifier: Programming Language :: Python :: 3 :: Only
Classifier: Programming Language :: Python :: 3.9
Classifier: Programming Language :: Python :: 3.10
Classifier: Programming Language :: Python :: 3.11
Classifier: Programming Language :: Python :: 3.12
Classifier: Topic :: Software Development :: Libraries
Classifier: Topic :: Software Development :: Libraries :: Python Modules
Classifier: Topic :: Utilities
Requires-Python: >=3.9
License-File: LICENSE
Requires-Dist: aiohttp
Requires-Dist: lxml >=4.9.2
Requires-Dist: lz4
Requires-Dist: pakler ~=0.2.0
Requires-Dist: pybcl ~=1.0.0
Requires-Dist: pycramfs ~=1.1.0
Requires-Dist: pyfdt >=0.3
Requires-Dist: PySquashfsImage ~=0.9.0
Requires-Dist: python-lzo ~=1.15
Requires-Dist: ubi-reader !=0.8.7,!=0.8.8
